PySimpleGUIQt.py
PySimpleGUIQt6-0.36.0.dist-info/METADATA
PySimpleGUIQt6-0.36.0.dist-info/WHEEL
PySimpleGUIQt6-0.36.0.dist-info/top_level.txt
PySimpleGUIQt6-0.36.0.dist-info/RECORD
